pgbelt/__init__.py
pgbelt/cmd/__init__.py
pgbelt/cmd/convenience.py
pgbelt/cmd/helpers.py
pgbelt/cmd/login.py
pgbelt/cmd/preflight.py
pgbelt/cmd/schema.py
pgbelt/cmd/setup.py
pgbelt/cmd/status.py
pgbelt/cmd/sync.py
pgbelt/cmd/teardown.py
pgbelt/config/__init__.py
pgbelt/config/config.py
pgbelt/config/models.py
pgbelt/config/remote.py
pgbelt/main.py
pgbelt/util/__init__.py
pgbelt/util/asyncfuncs.py
pgbelt/util/dump.py
pgbelt/util/logs.py
pgbelt/util/pglogical.py
pgbelt/util/postgres.py
pgbelt-0.8.3.dist-info/LICENSE
pgbelt-0.8.3.dist-info/METADATA
pgbelt-0.8.3.dist-info/WHEEL
pgbelt-0.8.3.dist-info/entry_points.txt
pgbelt-0.8.3.dist-info/RECORD
