Metadata-Version: 2.3
Name: pgbelt
Version: 0.8.3
Summary: A CLI tool used to manage Postgres data migrations from beginning to end, for a single database or a fleet, leveraging pglogical replication.
Author: Varjitt Jeeva
Author-email: varjitt.jeeva@autodesk.com
Requires-Python: >=3.9,<4.0
Classifier: Programming Language :: Python :: 3
Classifier: Programming Language :: Python :: 3.9
Classifier: Programming Language :: Python :: 3.10
Classifier: Programming Language :: Python :: 3.11
Classifier: Programming Language :: Python :: 3.12
Classifier: Programming Language :: Python :: 3.13
Requires-Dist: aiofiles (>=0.8,<24.2)
Requires-Dist: asyncpg (>=0.27,<0.31)
Requires-Dist: pydantic (>=2.0,<3.0)
Requires-Dist: tabulate (>=0.9.0,<0.10.0)
Requires-Dist: typer (>=0.9,<0.16)
